datawhale/__init__.py
datawhale/app.py
datawhale/config.py
datawhale/exceptions.py
datawhale/graph.py
datawhale/init.py
datawhale/local.py
datawhale/logging.py
datawhale/standard.py
datawhale/storage.py
datawhale/tasks.py
datawhale/app_pro/__init__.py
datawhale/app_pro/universe/__init__.py
datawhale/app_pro/universe/universe.py
datawhale/domain_pro/__init__.py
datawhale/domain_pro/data_standard.py
datawhale/domain_pro/tushare_config.py
datawhale/domain_pro/code_standard/__init__.py
datawhale/domain_pro/code_standard/decorators.py
datawhale/domain_pro/code_standard/interface.py
datawhale/domain_pro/code_standard/standardizer.py
datawhale/domain_pro/datetime_standard/__init__.py
datawhale/domain_pro/datetime_standard/datetime_utils.py
datawhale/domain_pro/datetime_standard/decorators.py
datawhale/domain_pro/field_standard/__init__.py
datawhale/domain_pro/field_standard/decorators.py
datawhale/domain_pro/field_standard/field_manager.py
datawhale/domain_pro/field_standard/fields.py
datawhale/domain_pro/field_standard/interface.py
datawhale/domain_pro/field_standard/standard_fields.py
datawhale/domain_pro/info_listing_and_delisting/__init__.py
datawhale/domain_pro/info_listing_and_delisting/listing_delisting_info.py
datawhale/domain_pro/info_st/__init__.py
datawhale/domain_pro/info_st/st_info.py
datawhale/domain_pro/info_suspend/__init__.py
datawhale/domain_pro/info_suspend/suspend_info.py
datawhale/domain_pro/info_trade_calendar/__init__.py
datawhale/domain_pro/info_trade_calendar/trade_calendar_info.py
datawhale/domain_pro/panel_new_stock/__init__.py
datawhale/domain_pro/panel_new_stock/new_stock_panel.py
datawhale/domain_pro/panel_st/__init__.py
datawhale/domain_pro/panel_st/st_panel.py
datawhale/domain_pro/panel_st/stock_st_status.py
datawhale/domain_pro/panel_trading_status/__init__.py
datawhale/domain_pro/panel_trading_status/stock_trading_status_marker.py
datawhale/domain_pro/panel_trading_status/trading_status_panel.py
datawhale/infrastructure_pro/__init__.py
datawhale-1.1.0rc3.dist-info/licenses/LICENSE
datawhale-1.1.0rc3.dist-info/METADATA
datawhale-1.1.0rc3.dist-info/WHEEL
datawhale-1.1.0rc3.dist-info/top_level.txt
datawhale-1.1.0rc3.dist-info/RECORD
