Metadata-Version: 2.4
Name: datawhale
Version: 1.1.0rc3
Summary: 金融数据平台，数据统一标准层。统一多数据源接口，可维护本地数据存储、更新
Author: 王工一念
Author-email: hans_wang@outlook.com
Classifier: Programming Language :: Python :: 3
Classifier: License :: OSI Approved :: BSD License
Classifier: Operating System :: OS Independent
Requires-Python: >=3.10
License-File: LICENSE
Requires-Dist: baostock>=0.8.9
Requires-Dist: pandas>=2.2.3
Requires-Dist: numpy>=1.26.0
Requires-Dist: tushare>=1.4.19
Requires-Dist: beautifulsoup4>=4.13.3
Requires-Dist: requests>=2.32.3
Requires-Dist: SQLAlchemy>=2.0.38
Requires-Dist: PyMySQL>=1.1.1
Requires-Dist: PyYAML>=6.0
Requires-Dist: graphviz>=0.20.0
Dynamic: author
Dynamic: author-email
Dynamic: classifier
Dynamic: description
Dynamic: description-content-type
Dynamic: license-file
Dynamic: requires-dist
Dynamic: requires-python
Dynamic: summary
